__init__.py
denormalized/__init__.py
denormalized/models.py
denormalized/tracker.py
denormalized/types.py
django_denormalized-1.0.0.dist-info/METADATA
django_denormalized-1.0.0.dist-info/WHEEL
django_denormalized-1.0.0.dist-info/top_level.txt
django_denormalized-1.0.0.dist-info/RECORD
