Metadata-Version: 2.1
Name: django_denormalized
Version: 1.0.0
Summary: Utils for maintaining denormalized aggregates for Django models
Author-email: Sergey Tikhonov <zimbler@gmail.com>
License: Beer License
Project-URL: Homepage, https://github.com/just-work/django-denormalized
Project-URL: Issues, https://github.com/just-work/django-denormalized/issues
Classifier: Programming Language :: Python :: 3
Classifier: License :: OSI Approved :: MIT License
Classifier: Operating System :: OS Independent
Requires-Python: >=3.7
Requires-Dist: Django <5.1,>=2.2
